README.md
setup.cfg
setup.py
gaussy/Binomialdistribution.py
gaussy/Gaussiandistribution.py
gaussy/Generaldistribution.py
gaussy/__init__.py
gaussy.egg-info/PKG-INFO
gaussy.egg-info/SOURCES.txt
gaussy.egg-info/dependency_links.txt
gaussy.egg-info/not-zip-safe
gaussy.egg-info/top_level.txt