Metadata-Version: 1.0
Name: gaussy
Version: 1.0
Summary: Gaussian distributions
Home-page: UNKNOWN
Author: Evalyne Ndanu Musili
Author-email: UNKNOWN
License: UNKNOWN
Platform: UNKNOWN
